sphinx_ubuntu_images/__init__.py
sphinx_ubuntu_images/_version.py
sphinx_ubuntu_images/common.py
sphinx_ubuntu_images/ubuntu_images.py
sphinx_ubuntu_images-0.1.0.dist-info/licenses/LICENSE
sphinx_ubuntu_images-0.1.0.dist-info/METADATA
sphinx_ubuntu_images-0.1.0.dist-info/WHEEL
sphinx_ubuntu_images-0.1.0.dist-info/top_level.txt
sphinx_ubuntu_images-0.1.0.dist-info/RECORD
